ufo_spacing_lib/__init__.py
ufo_spacing_lib/contexts.py
ufo_spacing_lib/groups_core.py
ufo_spacing_lib/margins_utils.py
ufo_spacing_lib/rules_constants.py
ufo_spacing_lib/rules_core.py
ufo_spacing_lib/rules_generator.py
ufo_spacing_lib/rules_manager.py
ufo_spacing_lib/rules_parser.py
ufo_spacing_lib/virtual.py
ufo_spacing_lib/commands/__init__.py
ufo_spacing_lib/commands/base.py
ufo_spacing_lib/commands/groups.py
ufo_spacing_lib/commands/kerning.py
ufo_spacing_lib/commands/margins.py
ufo_spacing_lib/commands/rules.py
ufo_spacing_lib/editors/__init__.py
ufo_spacing_lib/editors/kerning.py
ufo_spacing_lib/editors/margins.py
ufo_spacing_lib/editors/spacing.py
ufo_spacing_lib-0.4.1.dist-info/METADATA
ufo_spacing_lib-0.4.1.dist-info/WHEEL
ufo_spacing_lib-0.4.1.dist-info/licenses/LICENSE
ufo_spacing_lib-0.4.1.dist-info/RECORD
