Metadata-Version: 2.4
Name: ufo-spacing-lib
Version: 0.4.1
Summary: Font spacing management library for UFO-compatible fonts (kerning, margins, groups)
Project-URL: Homepage, https://github.com/typedev/ufo-spacing-lib
Project-URL: Repository, https://github.com/typedev/ufo-spacing-lib
Project-URL: Documentation, https://github.com/typedev/ufo-spacing-lib#readme
Project-URL: Issues, https://github.com/typedev/ufo-spacing-lib/issues
Author-email: Alexander Lubovenko <lubovenko@gmail.com>
License-Expression: MIT
License-File: LICENSE
Keywords: font,fonttools,kerning,spacing,type-design,typography,ufo
Classifier: Development Status :: 4 - Beta
Classifier: Intended Audience :: Developers
Classifier: License :: OSI Approved :: MIT License
Classifier: Operating System :: OS Independent
Classifier: Programming Language :: Python :: 3
Classifier: Programming Language :: Python :: 3.10
Classifier: Programming Language :: Python :: 3.11
Classifier: Programming Language :: Python :: 3.12
Classifier: Topic :: Multimedia :: Graphics :: Graphics Conversion
Classifier: Topic :: Text Processing :: Fonts
Classifier: Typing :: Typed
Requires-Python: >=3.10
Provides-Extra: dev
Requires-Dist: mypy; extra == 'dev'
Requires-Dist: pytest-cov; extra == 'dev'
Requires-Dist: pytest>=7.0; extra == 'dev'
Requires-Dist: ruff; extra == 'dev'
